an_branchrouter/__init__.py
an_branchrouter/branchrouter.py
an_branchrouter-0.2.1.dist-info/licenses/LICENSE
an_branchrouter-0.2.1.dist-info/METADATA
an_branchrouter-0.2.1.dist-info/WHEEL
an_branchrouter-0.2.1.dist-info/top_level.txt
an_branchrouter-0.2.1.dist-info/RECORD
