Metadata-Version: 2.4
Name: an_branchrouter
Version: 0.2.1
Summary: A package for an_branchrouter.
Home-page: https://github.com/Atsushi888/Atsushi888
Author: Atsushi888
Author-email: Atsushi888 <vtgrotxu@gmail.com>
Project-URL: Homepage, https://github.com/Atsushi888/an_branchrouter
Project-URL: Repository, https://github.com/Atsushi888/an_branchrouter
Requires-Python: >=3.6
License-File: LICENSE
Requires-Dist: an_DebugHelper
Requires-Dist: an_EnvManager
Requires-Dist: an_CudaUtility
Requires-Dist: an_CondaManager
Requires-Dist: an_KohyaSetupManager
Requires-Dist: an_DteSetupManager
Requires-Dist: an_ComfySetupManager
Requires-Dist: an_SDSetupManager
Dynamic: author
Dynamic: home-page
Dynamic: license-file
Dynamic: requires-python
